auto_dns/__init__.py
auto_dns/__main__.py
auto_dns/dns_providers/__init__.py
auto_dns/dns_providers/arvan.py
auto_dns/dns_providers/base.py
auto_dns/dns_providers/cloudflare.py
auto_dns/exceptions.py
auto_dns/main.py
auto_dns-0.1.2.dist-info/entry_points.txt
auto_dns-0.1.2.dist-info/WHEEL
auto_dns-0.1.2.dist-info/METADATA
auto_dns-0.1.2.dist-info/RECORD
